robosystems_client/__init__.py
robosystems_client/client.py
robosystems_client/errors.py
robosystems_client/py.typed
robosystems_client/sdk-config.yaml
robosystems_client/types.py
robosystems_client/api/__init__.py
robosystems_client/api/agent/__init__.py
robosystems_client/api/agent/auto_select_agent.py
robosystems_client/api/agent/batch_process_queries.py
robosystems_client/api/agent/execute_specific_agent.py
robosystems_client/api/agent/get_agent_metadata.py
robosystems_client/api/agent/list_agents.py
robosystems_client/api/agent/recommend_agent.py
robosystems_client/api/auth/__init__.py
robosystems_client/api/auth/check_password_strength.py
robosystems_client/api/auth/complete_sso_auth.py
robosystems_client/api/auth/forgot_password.py
robosystems_client/api/auth/generate_sso_token.py
robosystems_client/api/auth/get_captcha_config.py
robosystems_client/api/auth/get_current_auth_user.py
robosystems_client/api/auth/get_password_policy.py
robosystems_client/api/auth/login_user.py
robosystems_client/api/auth/logout_user.py
robosystems_client/api/auth/refresh_auth_session.py
robosystems_client/api/auth/register_user.py
robosystems_client/api/auth/resend_verification_email.py
robosystems_client/api/auth/reset_password.py
robosystems_client/api/auth/sso_token_exchange.py
robosystems_client/api/auth/validate_reset_token.py
robosystems_client/api/auth/verify_email.py
robosystems_client/api/backup/__init__.py
robosystems_client/api/backup/create_backup.py
robosystems_client/api/backup/get_backup_download_url.py
robosystems_client/api/backup/get_backup_stats.py
robosystems_client/api/backup/list_backups.py
robosystems_client/api/backup/restore_backup.py
robosystems_client/api/billing/__init__.py
robosystems_client/api/billing/cancel_org_subscription.py
robosystems_client/api/billing/create_checkout_session.py
robosystems_client/api/billing/create_portal_session.py
robosystems_client/api/billing/get_checkout_status.py
robosystems_client-0.2.25.dist-info/METADATA
robosystems_client-0.2.25.dist-info/WHEEL
robosystems_client-0.2.25.dist-info/licenses/LICENSE
robosystems_client-0.2.25.dist-info/RECORD
