Metadata-Version: 2.4
Name: robosystems-client
Version: 0.2.25
Summary: Python Client for RoboSystems financial graph database API
Author: RFS LLC
License: MIT
License-File: LICENSE
Keywords: api,client,financial,graph,robosystems,sdk
Classifier: Development Status :: 4 - Beta
Classifier: Framework :: AsyncIO
Classifier: Framework :: Pydantic
Classifier: Framework :: Pydantic :: 2
Classifier: Intended Audience :: Developers
Classifier: Intended Audience :: Financial and Insurance Industry
Classifier: License :: OSI Approved :: MIT License
Classifier: Natural Language :: English
Classifier: Operating System :: OS Independent
Classifier: Programming Language :: Python :: 3
Classifier: Programming Language :: Python :: 3.10
Classifier: Programming Language :: Python :: 3.11
Classifier: Programming Language :: Python :: 3.12
Classifier: Programming Language :: Python :: 3.13
Classifier: Topic :: Database :: Front-Ends
Classifier: Topic :: Internet :: WWW/HTTP
Classifier: Topic :: Office/Business :: Financial
Classifier: Topic :: Office/Business :: Financial :: Accounting
Classifier: Topic :: Software Development :: Libraries :: Python Modules
Classifier: Typing :: Typed
Requires-Python: >=3.10
Requires-Dist: attrs>=23.0.0
Requires-Dist: httpx>=0.28.1
Requires-Dist: pydantic>=2.11.7
Requires-Dist: python-dateutil>=2.8.0
Requires-Dist: typing-extensions>=4.0.0
Provides-Extra: all
Requires-Dist: pandas>=2.1.0; extra == 'all'
Requires-Dist: pyarrow>=17.0.0; extra == 'all'
Provides-Extra: dev
Requires-Dist: basedpyright>=1.21.0; extra == 'dev'
Requires-Dist: build>=1.0.0; extra == 'dev'
Requires-Dist: openapi-python-client>=0.21.8; extra == 'dev'
Requires-Dist: pytest-asyncio>=0.26.0; extra == 'dev'
Requires-Dist: pytest-httpx>=0.30.0; extra == 'dev'
Requires-Dist: pytest>=8.3.5; extra == 'dev'
Requires-Dist: ruff>=0.12; extra == 'dev'
Requires-Dist: twine>=5.0.0; extra == 'dev'
Provides-Extra: extensions
Requires-Dist: pandas>=2.1.0; extra == 'extensions'
Requires-Dist: pyarrow>=17.0.0; extra == 'extensions'
Provides-Extra: tables
Requires-Dist: pandas>=2.1.0; extra == 'tables'
Requires-Dist: pyarrow>=17.0.0; extra == 'tables'
